djinsight/__init__.py
djinsight/admin.py
djinsight/apps.py
djinsight/celery.py
djinsight/conf.py
djinsight/middleware.py
djinsight/models.py
djinsight/registry.py
djinsight/renderers.py
djinsight/tasks.py
djinsight/urls.py
djinsight/utils.py
djinsight/views.py
djinsight/management/__init__.py
djinsight/management/commands/__init__.py
djinsight/management/commands/cleanup_pageviews.py
djinsight/management/commands/generate_summaries.py
djinsight/management/commands/migrate_to_v2.py
djinsight/management/commands/process_pageviews.py
djinsight/mcp/__init__.py
djinsight/mcp/server.py
djinsight/migrations/0001_initial.py
djinsight/migrations/0002_rename_djinsight_p_page_id_a3ba77_idx_djinsight_p_page_id_f86134_idx_and_more.py
djinsight/migrations/0003_alter_pageviewlog_session_key.py
djinsight/migrations/0004_v2_new_architecture.py
djinsight/migrations/0005_mcpapikey_and_more.py
djinsight/migrations/__init__.py
djinsight/providers/__init__.py
djinsight/providers/base.py
djinsight/providers/database.py
djinsight/providers/redis.py
djinsight/templates/djinsight/tracking_script.html
djinsight/templates/djinsight/charts/default_chart.html
djinsight/templates/djinsight/widgets/stats_badge.html
djinsight/templates/djinsight/widgets/stats_widget.html
djinsight/templatetags/__init__.py
djinsight/templatetags/djinsight_tags.py
djinsight/tests/__init__.py
djinsight/tests/test_models.py
djinsight/tests/test_providers.py
djinsight/tests/test_views.py
djinsight-0.3.4.dist-info/licenses/LICENSE
djinsight-0.3.4.dist-info/METADATA
djinsight-0.3.4.dist-info/WHEEL
djinsight-0.3.4.dist-info/top_level.txt
djinsight-0.3.4.dist-info/RECORD
