Metadata-Version: 2.4
Name: djinsight
Version: 0.3.4
Summary: MCP-first analytics for Django/Wagtail package for tracking page view statistics with Redis and async processing
Home-page: https://github.com/krystianmagdziarz/djinsight
Author: MDigital
Author-email: MDigital <kontakt@mdigital.com.pl>
Maintainer-email: MDigital <kontakt@mdigital.com.pl>
License: MIT License
Project-URL: Homepage, https://github.com/krystianmagdziarz/djinsight
Project-URL: Documentation, https://djinsight.readthedocs.io/
Project-URL: Repository, https://github.com/krystianmagdziarz/djinsight.git
Project-URL: Bug Tracker, https://github.com/krystianmagdziarz/djinsight/issues
Project-URL: Changelog, https://github.com/krystianmagdziarz/djinsight/blob/main/CHANGELOG.md
Keywords: django,wagtail,analytics,statistics,page-views,redis,celery
Classifier: Development Status :: 5 - Production/Stable
Classifier: Environment :: Web Environment
Classifier: Framework :: Django
Classifier: Framework :: Django :: 3.2
Classifier: Framework :: Django :: 4.0
Classifier: Framework :: Django :: 4.1
Classifier: Framework :: Django :: 4.2
Classifier: Framework :: Django :: 5.0
Classifier: Framework :: Wagtail
Classifier: Framework :: Wagtail :: 3
Classifier: Framework :: Wagtail :: 4
Classifier: Framework :: Wagtail :: 5
Classifier: Intended Audience :: Developers
Classifier: License :: OSI Approved :: MIT License
Classifier: Operating System :: OS Independent
Classifier: Programming Language :: Python
Classifier: Programming Language :: Python :: 3
Classifier: Programming Language :: Python :: 3.8
Classifier: Programming Language :: Python :: 3.9
Classifier: Programming Language :: Python :: 3.10
Classifier: Programming Language :: Python :: 3.11
Classifier: Programming Language :: Python :: 3.12
Classifier: Topic :: Internet :: WWW/HTTP
Classifier: Topic :: Internet :: WWW/HTTP :: Dynamic Content
Classifier: Topic :: Software Development :: Libraries :: Python Modules
Requires-Python: >=3.8
License-File: LICENSE
Requires-Dist: Django>=3.2
Requires-Dist: wagtail>=3.0
Requires-Dist: redis>=4.0.0
Requires-Dist: celery>=5.0.0
Requires-Dist: django-redis>=5.0.0
Requires-Dist: django-environ>=0.9.0
Provides-Extra: dev
Requires-Dist: pytest>=6.0; extra == "dev"
Requires-Dist: pytest-django>=4.0; extra == "dev"
Requires-Dist: pytest-cov>=3.0; extra == "dev"
Requires-Dist: black>=22.0; extra == "dev"
Requires-Dist: flake8>=4.0; extra == "dev"
Requires-Dist: isort>=5.0; extra == "dev"
Requires-Dist: mypy>=0.900; extra == "dev"
Requires-Dist: factory-boy>=3.0; extra == "dev"
Provides-Extra: docs
Requires-Dist: sphinx>=4.0; extra == "docs"
Requires-Dist: sphinx-rtd-theme>=1.0; extra == "docs"
Provides-Extra: test
Requires-Dist: pytest>=6.0; extra == "test"
Requires-Dist: pytest-django>=4.0; extra == "test"
Requires-Dist: pytest-cov>=3.0; extra == "test"
Requires-Dist: factory-boy>=3.0; extra == "test"
Requires-Dist: coverage>=6.0; extra == "test"
Dynamic: author
Dynamic: home-page
Dynamic: license-file
Dynamic: requires-python
